ocxtools/__init__.py
ocxtools/cli.py
ocxtools/cli_plugin.py
ocxtools/clients/__init__.py
ocxtools/clients/clients.py
ocxtools/config.py
ocxtools/console/__init__.py
ocxtools/console/console.py
ocxtools/context/__init__.py
ocxtools/context/context_manager.py
ocxtools/converter/__init__.py
ocxtools/converter/converter.py
ocxtools/dataclass/__init__.py
ocxtools/dataclass/dataclasses.py
ocxtools/docker/README.md
ocxtools/docker/__init__.py
ocxtools/docker/cli.py
ocxtools/exceptions.py
ocxtools/interfaces/__init__.py
ocxtools/interfaces/interfaces.py
ocxtools/jupyter/__init__.py
ocxtools/jupyter/cli.py
ocxtools/jupyter/readme.md
ocxtools/loader/__init__.py
ocxtools/loader/loader.py
ocxtools/parser/__init__.py
ocxtools/parser/parser.py
ocxtools/rds/__init__.py
ocxtools/rds/cli.py
ocxtools/renderer/__init__.py
ocxtools/renderer/cli.py
ocxtools/renderer/renderer.py
ocxtools/reporter/__init__.py
ocxtools/reporter/cli.py
ocxtools/reporter/report_manager.py
ocxtools/reporter/reporter.py
ocxtools/serializer/__init__.py
ocxtools/serializer/cli.py
ocxtools/serializer/resource/gitb_trl_stylesheet_v1.0.xsl
ocxtools/serializer/serializer.py
ocxtools/utils/__init__.py
ocxtools/utils/utilities.py
ocxtools/validator/__init__.py
ocxtools/validator/cli.py
ocxtools/validator/validator_client.py
ocxtools/validator/validator_report.py
ocxtools-1.5.3.dist-info/LICENSE
ocxtools-1.5.3.dist-info/METADATA
ocxtools-1.5.3.dist-info/WHEEL
ocxtools-1.5.3.dist-info/entry_points.txt
ocxtools-1.5.3.dist-info/RECORD
