Metadata-Version: 2.1
Name: ocxtools
Version: 1.5.3
Summary: Python utility CLI for working with 3Docx models.
Author: ocastrup
Author-email: ole.christian.astrup@dnv.com
Requires-Python: >=3.10,<4.0
Classifier: Programming Language :: Python :: 3
Classifier: Programming Language :: Python :: 3.10
Classifier: Programming Language :: Python :: 3.11
Classifier: Programming Language :: Python :: 3.12
Classifier: Programming Language :: Python :: 3.13
Requires-Dist: arrow
Requires-Dist: click
Requires-Dist: click_shell
Requires-Dist: fastparquet (>=2024.2.0,<2025.0.0)
Requires-Dist: httpx
Requires-Dist: loguru
Requires-Dist: lxml
Requires-Dist: ocx (==3.0.1)
Requires-Dist: ocx_schema_parser (==1.7.1)
Requires-Dist: openpyxl (>=3.1.2,<4.0.0)
Requires-Dist: packaging (>=23.1,<24.0)
Requires-Dist: pandas
Requires-Dist: pyarrow (>=15.0.0,<16.0.0)
Requires-Dist: rich
Requires-Dist: soap
Requires-Dist: tbump
Requires-Dist: typer
